lsst/__init__.py
lsst/sphgeom/__init__.py
lsst/sphgeom/_angle.cc
lsst/sphgeom/_angleInterval.cc
lsst/sphgeom/_box.cc
lsst/sphgeom/_box3d.cc
lsst/sphgeom/_chunker.cc
lsst/sphgeom/_circle.cc
lsst/sphgeom/_compoundRegion.cc
lsst/sphgeom/_continue_class.py
lsst/sphgeom/_convexPolygon.cc
lsst/sphgeom/_curve.cc
lsst/sphgeom/_ellipse.cc
lsst/sphgeom/_healpixPixelization.py
lsst/sphgeom/_htmPixelization.cc
lsst/sphgeom/_interval1d.cc
lsst/sphgeom/_lonLat.cc
lsst/sphgeom/_matrix3d.cc
lsst/sphgeom/_mq3cPixelization.cc
lsst/sphgeom/_normalizedAngle.cc
lsst/sphgeom/_normalizedAngleInterval.cc
lsst/sphgeom/_orientation.cc
lsst/sphgeom/_pixelization.cc
lsst/sphgeom/_q3cPixelization.cc
lsst/sphgeom/_rangeSet.cc
lsst/sphgeom/_region.cc
lsst/sphgeom/_relationship.cc
lsst/sphgeom/_sphgeom.cc
lsst/sphgeom/_sphgeom.cpython-313-aarch64-linux-gnu.so
lsst/sphgeom/_unitVector3d.cc
lsst/sphgeom/_utils.cc
lsst/sphgeom/_vector3d.cc
lsst/sphgeom/_yaml.py
lsst/sphgeom/pixelization_abc.py
lsst/sphgeom/version.py
lsst_sphgeom-30.0.0.dist-info/METADATA
lsst_sphgeom-30.0.0.dist-info/WHEEL
lsst_sphgeom-30.0.0.dist-info/top_level.txt
lsst_sphgeom-30.0.0.dist-info/RECORD
lsst_sphgeom-30.0.0.dist-info/licenses/COPYRIGHT
lsst_sphgeom-30.0.0.dist-info/licenses/LICENSE
lsst_sphgeom-30.0.0.dist-info/licenses/bsd_license.txt
lsst_sphgeom-30.0.0.dist-info/licenses/gpl-v3.0.txt
