Metadata-Version: 2.4
Name: lsst-sphgeom
Version: 30.0.0
Summary: A spherical geometry library.
Author-email: Rubin Observatory Data Management <dm-admin@lists.lsst.org>
License-Expression: BSD-3-Clause OR GPL-3.0-or-later
Project-URL: Homepage, https://github.com/lsst/sphgeom
Keywords: lsst
Classifier: Intended Audience :: Science/Research
Classifier: Operating System :: POSIX :: Linux
Classifier: Operating System :: MacOS :: MacOS X
Classifier: Programming Language :: Python :: 3
Classifier: Programming Language :: Python :: 3.10
Classifier: Programming Language :: Python :: 3.11
Classifier: Programming Language :: Python :: 3.12
Classifier: Programming Language :: Python :: 3.13
Classifier: Programming Language :: Python :: 3.14
Classifier: Topic :: Scientific/Engineering :: Astronomy
Requires-Python: >=3.10.0
License-File: COPYRIGHT
License-File: LICENSE
License-File: bsd_license.txt
License-File: gpl-v3.0.txt
Requires-Dist: numpy>=1.18
Requires-Dist: hpgeom>=0.8.0
Provides-Extra: test
Requires-Dist: pytest>=3.2; extra == "test"
Provides-Extra: yaml
Requires-Dist: pyyaml>=5.1; extra == "yaml"
Dynamic: license-file
